protecc/__init__.py
protecc-0.0.2.dist-info/LICENSE
protecc-0.0.2.dist-info/METADATA
protecc-0.0.2.dist-info/WHEEL
protecc-0.0.2.dist-info/top_level.txt
protecc-0.0.2.dist-info/RECORD
