Metadata-Version: 2.1
Name: protecc
Version: 0.0.2
Summary: Access modifiers for python
Home-page: https://github.com/avinashshenoy97/protecc
Author: Avinash Shenoy
Author-email: avi123shenoy@gmail.com
License: UNKNOWN
Platform: UNKNOWN
Classifier: Programming Language :: Python :: 3
Classifier: License :: OSI Approved :: MIT License
Classifier: Operating System :: OS Independent
